Metadata-Version: 2.1
Name: mailengine
Version: 1.0
Summary: A Tool For Sending Mails And Send OTP
Home-page: https://pypi.org/project/mailengine
Author: rajyavardhan_bithale
Author-email: bithale03@protonmail.com
License: UNKNOWN
Project-URL: Bug Tracker, https://github.com/pypa/sampleproject/issues
Platform: UNKNOWN
Classifier: Programming Language :: Python :: 3
Classifier: License :: OSI Approved :: MIT License
Classifier: Operating System :: OS Independent
Requires-Python: >=3.6
